{
  "id": "skystreet7",
  "name": "スカイストリートちほー7",
  "comment": "『やり直す前の世界』を恐れる必要はもうないんだ",
  "area": "タイムリープを繰り返し、ようやくたどり着いた未来。絡まった糸の根本にたどり着ければ、ようやく掴んだ『現在』もなかった事になるかもしれない。その重い現実に、全員黙り込んだ。",
  "youtubeID": "x6tEQzfNbOg",
  "characters": [
    {
      "name": "トキヤ（ぬいぐるみ）",
      "summary": "モモのお手製のトキヤぬい。\r\n裁縫は苦手だったが、ネットを見つつ頑張って仕上げた。\r\nアシメヘアーの再現が一番難しかった。",
      "title1": "身長",
      "item1": "28cm",
      "title2": "制作日",
      "item2": "4月30日",
      "title3": "年齢",
      "item3": ":0歳",
      "serif": "やだ、すっごい似てるかも～！？（モモ）",
      "team": "モモの部屋",
      "illustrator": "たま",
      "img": "01"
    },
    {
      "name": "モモ",
      "summary": "繰り返す日々の中で、心に引っかかった色々な出来事。\r\n届けられなかった言葉を、紙にのせる。\r\nいつか、この言の葉達を君の音に乗せてくれる事を願って。",
      "title1": "身長",
      "item1": "157.5cm",
      "title2": "誕生日",
      "item2": "4月1日",
      "title3": "年齢",
      "item3": "16歳",
      "serif": "私の言葉はもうトキヤに届いた\r\n大丈夫。次はあなたの番",
      "team": "REAL VOICE",
      "illustrator": "たま",
      "img": "02"
    },
    {
      "name": "コハク",
      "summary": "蜘蛛の巣のように、ヒントを張り巡らせる。\r\nこの街の蝶が、ひらひらと舞ってからめとられるように。\r\n路地裏の蝶のマーク、その座標が手始めの暗号。",
      "title1": "身長",
      "item1": "163cm",
      "title2": "誕生日",
      "item2": "9月7日",
      "title3": "年齢",
      "item3": "17歳",
      "serif": "出来損ないの魔法使い\r\n……でも『私の願い』は？\r\n一度でもかなえようとした？",
      "team": "無所属",
      "illustrator": "沙月",
      "img": "03"
    },
    {
      "name": "ノア",
      "summary": "私の望みは、暁の願いをかなえること\r\nでも本当は、私が必要だって言ってほしかっただけ。",
      "title1": "身長",
      "item1": "？",
      "title2": "誕生日",
      "item2": "？",
      "title3": "年齢",
      "item3": "？",
      "serif": "コハクが願うなら\n私と暁も、やっとこのループを\r\n終わらせられる",
      "team": "ラウム",
      "illustrator": "ヨ剤",
      "img": "04"
    }
  ],
  "songs": [
    {
      "songtitle": "スローグロー",
      "artist": "nayuta、櫻澤ヒカル",
      "movie": "DaLq",
      "illustrator": "たま",
      "songsummary": "『繰り返す日々の中、ふと見つけたもの\r\n綺麗な物\r\n誰かと笑う瞬間\r\nたまに掛け違えるボタン\r\nそう言う、心にひっかかった物を文字に残していた\r\n\r\nいつか、また君に届くように\r\n君の音階の上で遊ぶ言葉を感じたいから』\r\n\r\nそう思って私は時をこえた。何度やり直したとしても、私は同じ選択をすると思う。\r\nだから、もう大丈夫。次はあなたの願いをかなえて。",
      "thumbnail": "skystreet7-01"
    },
    {
      "songtitle": "ECHO,",
      "artist": "棗いつき、櫻澤ヒカル",
      "movie": "びーすけ",
      "illustrator": "沙月",
      "songsummary": "『電子の海にひらひらと舞う幻の蝶\r\nそれさえ捕まえられれば、何もかも解決する\r\nそう信じて、街の住人は蝶のマークを手掛かりに、ネットの海で私の居所を探す\r\n路地裏の蝶のポイント\r\nその座標の数字が手始めの暗号\r\n\r\n私が、全ての願いを叶える事は出来ない、偽りの魔法使いであっても』\r\n\r\n何度も何度も繰り返してわかった事。\r\n神様は、私たちの願いなんてかなえてくれない。\r\nだけどもう一度、私自身の為だけにC204を使うとしたら、何を選ぶだろう？",
      "thumbnail": "skystreet7-02"
    },
    {
      "songtitle": "Phase: Theatre",
      "artist": "藍月なくる、櫻澤ヒカル",
      "movie": "tugutugu",
      "illustrator": "ヨ剤",
      "songsummary": "『ラウムの白い実験棟\r\nそこにはにせものが並んでいる\r\n私は31番目のにせもの\r\n\r\n何度ここから飛び降りても変わらないのは\r\n貴方自身が一番わかってるでしょう？』\r\n\r\n私と暁が消える世界線\r\n私達、それをずっと探していたのかもしれない。",
      "thumbnail": "skystreet7-03"
    },
    {
      "songtitle": "Sky Trails",
      "artist": "La prière、RD-Sounds",
      "movie": "INPINE",
      "illustrator": "Masako Wada",
      "songsummary": "何度もやり直して、やっとたどり着いた未来。\r\n手放す事が怖くないと言ったら嘘になる。\r\n後悔しないなんて保証もない。\r\nでも、何度もあがいたから、わかる事がある。\r\n\r\nもう、私達は\r\n遥か未来で、過去で、\r\n掴みたい世界を、自分で選ぶことができる。\r\n\r\n全てやり直して、この記憶が、無くなってしまったとしてもきっと。\r\n\r\nだから今度は、コハクとアカツキの番。\r\nさあ、あなた達は何を選ぶ？",
      "thumbnail": "skystreet7-04"
    }
  ]
}
